gmalglib/__init__.py
gmalglib/core.cp38-win_amd64.pyd
gmalglib/sm2.py
gmalglib/sm2.pyi
gmalglib/sm3.py
gmalglib/sm3.pyi
gmalglib/sm4.py
gmalglib/sm4.pyi
gmalglib/wrapped.py
gmalglib/zuc.py
gmalglib/zuc.pyi
gmalglib-0.5.9.dist-info/LICENSE
gmalglib-0.5.9.dist-info/METADATA
gmalglib-0.5.9.dist-info/WHEEL
gmalglib-0.5.9.dist-info/top_level.txt
gmalglib-0.5.9.dist-info/RECORD
