Metadata-Version: 2.1
Name: gmalglib
Version: 0.5.9
Summary: Python package implementing GM algorithms in C.
Author-email: ww-rm <ww-rm@qq.com>
Project-URL: Homepage, https://github.com/ww-rm/gmalglib
Project-URL: Issues, https://github.com/ww-rm/gmalglib/issues
Project-URL: Documentation, https://gmalglib.readthedocs.io
Classifier: Programming Language :: C
Classifier: Programming Language :: Python :: 3
Classifier: License :: OSI Approved :: MIT License
Classifier: Operating System :: OS Independent
Classifier: Topic :: Security :: Cryptography
Requires-Python: >=3.8
License-File: LICENSE
